{"filename":"/data/__azurite_db_queue_extent__.json","collections":[{"name":"$EXTENTS_COLLECTION$","data":[{"id":"4dcdaee7-59df-4125-b32a-7ef6c2357fb3","locationId":"Default","path":"4dcdaee7-59df-4125-b32a-7ef6c2357fb3","size":6500,"lastModifiedInMS":1587996826978,"meta":{"revision":499,"created":1587996826980,"version":0,"updated":1587996836926},"$loki":1,"LastModifyInMS":1587996836926},{"id":"d8de992a-b5ff-4125-95b1-304d60ab023e","locationId":"Default","path":"d8de992a-b5ff-4125-95b1-304d60ab023e","size":10543,"lastModifiedInMS":1587996917070,"meta":{"revision":810,"created":1587996917071,"version":0,"updated":1587996927107},"$loki":2,"LastModifyInMS":1587996927106},{"id":"fa5b6934-b451-4035-bad1-5893f6ad8e55","locationId":"Default","path":"fa5b6934-b451-4035-bad1-5893f6ad8e55","size":7124,"lastModifiedInMS":1587996993703,"meta":{"revision":547,"created":1587996993704,"version":0,"updated":1587997003840},"$loki":3,"LastModifyInMS":1587997003840},{"id":"5ec178d8-92e9-4989-994f-eb6d568bfd57","locationId":"Default","path":"5ec178d8-92e9-4989-994f-eb6d568bfd57","size":6500,"lastModifiedInMS":1587997046735,"meta":{"revision":499,"created":1587997046736,"version":0,"updated":1587997056616},"$loki":4,"LastModifyInMS":1587997056616},{"id":"05351fb9-a63d-40fe-969b-8fb09d848b00","locationId":"Default","path":"05351fb9-a63d-40fe-969b-8fb09d848b00","size":7137,"lastModifiedInMS":1587997185351,"meta":{"revision":548,"created":1587997185353,"version":0,"updated":1587997195419},"$loki":5,"LastModifyInMS":1587997195419}],"idIndex":[1,2,3,4,5],"binaryIndices":{"id":{"name":"id","dirty":false,"values":[4,0,3,1,2]}},"constraints":null,"uniqueNames":[],"transforms":{},"objType":"$EXTENTS_COLLECTION$","dirty":false,"cachedIndex":null,"cachedBinaryIndex":null,"cachedData":null,"adaptiveBinaryIndices":true,"transactional":false,"cloneObjects":false,"cloneMethod":"parse-stringify","asyncListeners":false,"disableMeta":false,"disableChangesApi":true,"disableDeltaChangesApi":true,"autoupdate":false,"serializableIndices":true,"ttl":null,"maxId":5,"DynamicViews":[],"events":{"insert":[],"update":[],"pre-insert":[],"pre-update":[],"close":[],"flushbuffer":[],"error":[],"delete":[null],"warning":[null]},"changes":[]}],"databaseVersion":1.5,"engineVersion":1.5,"autosave":true,"autosaveInterval":5000,"autosaveHandle":null,"throttledSaves":true,"options":{"autosave":true,"autosaveInterval":5000,"serializationMethod":"normal","destructureDelimiter":"$<\n"},"persistenceMethod":"fs","persistenceAdapter":null,"verbose":false,"events":{"init":[null],"loaded":[],"flushChanges":[],"close":[],"changes":[],"warning":[]},"ENV":"NODEJS"}